{
  "title": "A Lamb Goes Uncomplaining Forth",
  "key": "F major",
  "key_root": "F",
  "mode": "major",
  "meter": "4/4",
  "bpm": 100,
  "words": "Paul Gerhardt, 1648.  Translation composite",
  "music": "Wolfgang Dachstein, 1525",
  "tune": "An Wasserflüssen Babylon",
  "lyrics": {
    "v1": "A Lamb goes uncomplaining forth, The guilt of all men bearing; And laden with the sins of earth, None else the burden sharing! Goes patient on, grow weak and faint, To slaughter led without complaint, That spotless life to offer; Bears shame and stripes, and wounds and death, Anguish and mockery, and saith, &quot;Willing all this I suffer.&quot;",
    "v2": "This Lamb is Christ, the soul&#39;s great Friend, The Lamb of God, our Savior; Him God the Father chose to send To gain for us His favor. &quot;Go forth, My Son,&quot; the Father saith, &quot;And free men from the fear of death, From guilt and condemnation. The wrath and stripes are hard to bear, But by Thy Passion men shall share The fruit of Thy salvation.&quot;",
    "v3": "&quot;Yea, Father, yea, most willingly I&#39;ll bear what Thou commandest; My will conforms to Thy decree, I do what Thou demandest.&quot; O wondrous Love, what hast Thou done! The Father offers up His Son! The Son, content, descendeth! O Love, how strong Thou art to save! Thou beddest Him within the grave Whose word the mountains rendeth.",
    "v4": "Thou lay&#39;st Him, Love, upon the cross, With nails and spear Him bruising; Thou slay&#39;st Him as a lamb, His loss from soul and body oozing; From body &#39;tis the crimson flood Of precious sacrificial blood From soul, the strength of anguish: My gain it is; sweet Lamb to Thee What can I give, whose love to me For me doth make Thee languish?",
    "v5": "Lord, all my life I&#39;ll cleave to Thee, Thy love fore&#39;er beholding, Thee ever, as Thou ever me, With loving arms enfolding. Yea, Thou shalt be my Beaconlight, To guide me safe through death&#39;s dark night. And cheer my heart in sorrow; Henceforth myself and all that&#39;s mine To Thee, my Savior, I consign, From whom all things I borrow."
  },
  "phrases": [
    {
      "label": "A",
      "bars": [
        1,
        2,
        3
      ],
      "strategy": "melody falls — breathes",
      "cycle": "3rds CCW",
      "cycle_color": "leafred",
      "lyrics": {
        "v1": "A Lamb goes uncomplaining forth,",
        "v2": "This Lamb is Christ, the soul&#39;s great Friend,"
      }
    },
    {
      "label": "B",
      "bars": [
        4,
        5,
        6
      ],
      "strategy": "melody circles — breathes",
      "cycle": "4ths CW",
      "cycle_color": "leafyellow",
      "lyrics": {
        "v1": "The guilt of all men bearing;",
        "v2": "The Lamb of God, our Savior;"
      }
    },
    {
      "label": "C",
      "bars": [
        7,
        8,
        9
      ],
      "strategy": "melody falls — breathes",
      "cycle": "3rds CCW",
      "cycle_color": "leafred",
      "lyrics": {
        "v1": "And laden with the sins of earth,",
        "v2": "Him God the Father chose to send"
      }
    },
    {
      "label": "D",
      "bars": [
        10,
        11,
        12
      ],
      "strategy": "melody circles — breathes",
      "cycle": "4ths CW",
      "cycle_color": "leafyellow",
      "lyrics": {
        "v1": "None else the burden sharing!",
        "v2": "To gain for us His favor."
      }
    },
    {
      "label": "E",
      "bars": [
        13,
        14,
        15
      ],
      "strategy": "melody circles — breathes",
      "cycle": "4ths CCW",
      "cycle_color": "leafyellow",
      "lyrics": {
        "v1": "Goes patient on, grow weak and faint,",
        "v2": "&quot;Go forth, My Son,&quot; the Father saith,"
      }
    },
    {
      "label": "F",
      "bars": [
        16,
        17,
        18,
        19,
        20,
        21,
        22,
        23
      ],
      "strategy": "melody rises — breathes",
      "cycle": "2nds CW",
      "cycle_color": "leafcyan",
      "lyrics": {
        "v1": "To slaughter led without complaint, That spotless life to offer; Bears shame and stripes, and",
        "v2": "&quot;And free men from the fear of death, From guilt and condemnation. The wrath and stripes are"
      }
    },
    {
      "label": "G",
      "bars": [
        24,
        25,
        26,
        27,
        28,
        29
      ],
      "strategy": "melody falls — breathes",
      "cycle": "stacked",
      "cycle_color": "accent",
      "lyrics": {
        "v1": "wounds and death, Anguish and mockery, and saith, &quot;Will",
        "v2": "hard to bear, But by Thy Passion men shall share The"
      }
    },
    {
      "label": "H",
      "bars": [
        30,
        31,
        32
      ],
      "strategy": "melody circles — closes home",
      "cycle": "stacked",
      "cycle_color": "accent",
      "lyrics": {
        "v1": "ing all this I suffer.&quot;",
        "v2": "fruit of Thy salvation.&quot;"
      }
    }
  ],
  "assignments": [
    {
      "bar": 1,
      "rn": "I",
      "mel": "C5",
      "lh_rom": "vi",
      "lh_qual": "",
      "lh_fig": "633",
      "rh_rom": "I",
      "rh_qual": "",
      "rh_fig": "F33",
      "mood": "Brooding",
      "source": "jazz_progressions"
    },
    {
      "bar": 2,
      "rn": "vi",
      "mel": "A4",
      "lh_rom": "IV",
      "lh_qual": "",
      "lh_fig": "433",
      "rh_rom": "vi",
      "rh_qual": "",
      "rh_fig": "D33",
      "mood": "Consoling",
      "source": "jazz_progressions"
    },
    {
      "bar": 3,
      "rn": "IV",
      "mel": "B-4",
      "lh_rom": "IV",
      "lh_qual": "",
      "lh_fig": "433",
      "rh_rom": "V",
      "rh_qual": "",
      "rh_fig": "C33",
      "mood": "Tensing",
      "source": "jazz_progressions"
    },
    {
      "bar": 4,
      "rn": "V",
      "mel": "G4",
      "lh_rom": "IΔii",
      "lh_qual": "",
      "lh_fig": "5323",
      "rh_rom": "V7iii",
      "rh_qual": "",
      "rh_fig": "B233",
      "mood": "Resolving",
      "source": "jazz_progressions"
    },
    {
      "bar": 5,
      "rn": "I6",
      "mel": "C5",
      "lh_rom": "I6",
      "lh_qual": "",
      "lh_fig": "1332",
      "rh_rom": "V7i",
      "rh_qual": "",
      "rh_fig": "7332",
      "mood": "Warm",
      "source": "stacked_chords"
    },
    {
      "bar": 6,
      "rn": "I",
      "mel": "G4",
      "lh_rom": "vi",
      "lh_qual": "",
      "lh_fig": "633",
      "rh_rom": "I",
      "rh_qual": "",
      "rh_fig": "F33",
      "mood": "Brooding",
      "source": "jazz_progressions"
    },
    {
      "bar": 8,
      "rn": "vi",
      "mel": "A4",
      "lh_rom": "IV",
      "lh_qual": "",
      "lh_fig": "433",
      "rh_rom": "vi",
      "rh_qual": "",
      "rh_fig": "D33",
      "mood": "Consoling",
      "source": "jazz_progressions"
    },
    {
      "bar": 9,
      "rn": "IV",
      "mel": "B-4",
      "lh_rom": "IV",
      "lh_qual": "",
      "lh_fig": "433",
      "rh_rom": "V",
      "rh_qual": "",
      "rh_fig": "C33",
      "mood": "Tensing",
      "source": "jazz_progressions"
    },
    {
      "bar": 10,
      "rn": "V",
      "mel": "G4",
      "lh_rom": "IΔii",
      "lh_qual": "",
      "lh_fig": "5323",
      "rh_rom": "V7iii",
      "rh_qual": "",
      "rh_fig": "B233",
      "mood": "Resolving",
      "source": "jazz_progressions"
    },
    {
      "bar": 11,
      "rn": "I6",
      "mel": "C5",
      "lh_rom": "I6",
      "lh_qual": "",
      "lh_fig": "1332",
      "rh_rom": "V7i",
      "rh_qual": "",
      "rh_fig": "7332",
      "mood": "Warm",
      "source": "stacked_chords"
    },
    {
      "bar": 12,
      "rn": "I",
      "mel": "G4",
      "lh_rom": "IVΔii",
      "lh_qual": "",
      "lh_fig": "1323",
      "rh_rom": "IΔiii",
      "rh_qual": "",
      "rh_fig": "7233",
      "mood": "Exploring",
      "source": "jazz_progressions"
    },
    {
      "bar": 14,
      "rn": "IV",
      "mel": "B-4",
      "lh_rom": "I",
      "lh_qual": "",
      "lh_fig": "133",
      "rh_rom": "IV",
      "rh_qual": "",
      "rh_fig": "B33",
      "mood": "Landing",
      "source": "jazz_progressions"
    },
    {
      "bar": 15,
      "rn": "I",
      "mel": "A4",
      "lh_rom": "IVΔii",
      "lh_qual": "",
      "lh_fig": "1323",
      "rh_rom": "IΔiii",
      "rh_qual": "",
      "rh_fig": "7233",
      "mood": "Exploring",
      "source": "jazz_progressions"
    },
    {
      "bar": 16,
      "rn": "IV",
      "mel": "F4",
      "lh_rom": "V7iii",
      "lh_qual": "",
      "lh_fig": "4233",
      "rh_rom": "IVΔiii",
      "rh_qual": "",
      "rh_fig": "A233",
      "mood": "Tensing",
      "source": "jazz_progressions"
    },
    {
      "bar": 17,
      "rn": "V",
      "mel": "C5",
      "lh_rom": "V",
      "lh_qual": "",
      "lh_fig": "533",
      "rh_rom": "vi",
      "rh_qual": "",
      "rh_fig": "D33",
      "mood": "Deceptive",
      "source": "jazz_progressions"
    },
    {
      "bar": 18,
      "rn": "vi",
      "mel": "A4",
      "lh_rom": "vi",
      "lh_qual": "",
      "lh_fig": "633",
      "rh_rom": "I",
      "rh_qual": "",
      "rh_fig": "F33",
      "mood": "Triumphing",
      "source": "jazz_progressions"
    },
    {
      "bar": 20,
      "rn": "I43",
      "mel": "C5",
      "lh_rom": "ii7iii",
      "lh_qual": "",
      "lh_fig": "1233",
      "rh_rom": "IΔiii",
      "rh_qual": "",
      "rh_fig": "7233",
      "mood": "Cloudy",
      "source": "jazz_progressions"
    },
    {
      "bar": 21,
      "rn": "ii64",
      "mel": "B-4",
      "lh_rom": "ii",
      "lh_qual": "",
      "lh_fig": "233",
      "rh_rom": "vi",
      "rh_qual": "",
      "rh_fig": "D33",
      "mood": "Dreaming",
      "source": "jazz_progressions"
    },
    {
      "bar": 22,
      "rn": "vi",
      "mel": "D5",
      "lh_rom": "V",
      "lh_qual": "",
      "lh_fig": "533",
      "rh_rom": "vi",
      "rh_qual": "",
      "rh_fig": "D33",
      "mood": "Pivoting",
      "source": "jazz_progressions"
    },
    {
      "bar": 23,
      "rn": "V7",
      "mel": "G4",
      "lh_rom": "ii",
      "lh_qual": "",
      "lh_fig": "233",
      "rh_rom": "V",
      "rh_qual": "",
      "rh_fig": "C33",
      "mood": "Stepping",
      "source": "jazz_progressions"
    },
    {
      "bar": 24,
      "rn": "ii64",
      "mel": "B-4",
      "lh_rom": "ii",
      "lh_qual": "",
      "lh_fig": "233",
      "rh_rom": "vii°",
      "rh_qual": "",
      "rh_fig": "733",
      "mood": "Tilting",
      "source": "jazz_progressions"
    },
    {
      "bar": 25,
      "rn": "ii",
      "mel": "G4",
      "lh_rom": "ii",
      "lh_qual": "",
      "lh_fig": "233",
      "rh_rom": "V",
      "rh_qual": "",
      "rh_fig": "C33",
      "mood": "Lifting",
      "source": "jazz_progressions"
    },
    {
      "bar": 26,
      "rn": "ii7",
      "mel": "B-4",
      "lh_rom": "ii",
      "lh_qual": "",
      "lh_fig": "233",
      "rh_rom": "vi",
      "rh_qual": "",
      "rh_fig": "D33",
      "mood": "Dreaming",
      "source": "jazz_progressions"
    },
    {
      "bar": 27,
      "rn": "vi7",
      "mel": "F4",
      "lh_rom": "V",
      "lh_qual": "",
      "lh_fig": "533",
      "rh_rom": "vi",
      "rh_qual": "",
      "rh_fig": "D33",
      "mood": "Pivoting",
      "source": "jazz_progressions"
    },
    {
      "bar": 28,
      "rn": "V52",
      "mel": "E4",
      "lh_rom": "V",
      "lh_qual": "",
      "lh_fig": "533",
      "rh_rom": "I",
      "rh_qual": "",
      "rh_fig": "F33",
      "mood": "Resolving",
      "source": "jazz_progressions"
    },
    {
      "bar": 29,
      "rn": "I62",
      "mel": "C4",
      "lh_rom": "I6",
      "lh_qual": "",
      "lh_fig": "1332",
      "rh_rom": "V7i",
      "rh_qual": "",
      "rh_fig": "7332",
      "mood": "Warm",
      "source": "stacked_chords"
    },
    {
      "bar": 30,
      "rn": "I",
      "mel": "F4",
      "lh_rom": "I",
      "lh_qual": "",
      "lh_fig": "133",
      "rh_rom": "IV",
      "rh_qual": "",
      "rh_fig": "B33",
      "mood": "Exploring",
      "source": "jazz_progressions"
    },
    {
      "bar": 31,
      "rn": "I52",
      "mel": "C5",
      "lh_rom": "I6",
      "lh_qual": "",
      "lh_fig": "1332",
      "rh_rom": "V7i",
      "rh_qual": "",
      "rh_fig": "7332",
      "mood": "Warm",
      "source": "stacked_chords"
    }
  ],
  "total_bars": 32
}