{
  "title": "O Holy Spirit, Enter In",
  "key": "E♭ major",
  "key_root": "E-",
  "mode": "major",
  "meter": "4/4",
  "bpm": 100,
  "words": "Michael Schirmer, 1650 except verse 2 by unknown author circa 1660 Verses 1, 4, 6-8 translated by by Catherine Winkworth, 1863.  Remaining verses unknown translator before 1931",
  "music": "Phillipp Nicolai, 1599",
  "tune": "Wie Schön Leuchtet",
  "lyrics": {
    "v1": "O Holy Spirit, enter in, And in our hearts Thy work begin Thy Temple deign to make us; Sun of the soul, Thou Light divine, Around and in us brightly shine, To joy and gladness wake us. That we to Thee Truly living, To Thee giving Prayer unceasing May in love be still increasing.",
    "v2": "Give to Thy Word impressive pow&#39;r That in our hearts, from this good hour, As fire it may be glowing; That we confess the Father, Son, And Thee, the Spirit, Three in One, Thy glory ever showing. Stay Thou, guide now Our souls ever that they never May forsake Thee. But by faith their refuge make Thee.",
    "v3": "Thou fountain whence all wisdom flows Which God on pious hearts bestows, Grant us Thy consolation. That in our pure faith&#39;s uni- ty We faithful witnesses may be Of grace that brings salvation. Hear us, cheer us, By Thy teaching; let our preaching, And our labor Praise Thee, Lord, and serve our neighbor.",
    "v4": "Left to ourselves, we shall but stray; O lead us on the narrow way, With wisest counsel guide us; And give us steadfastness, that we May ever faithful prove to Thee, Whatever woes betide us; Lord now Heal Thou All hearts broken, And betoken Thou art near us, Whom we trust to light and cheer us.",
    "v5": "Thy heav&#39;nly strength sustain our heart That we may act the valiant part With Thee as our Reliance; Be Thou our Refuge and our Shield That we may never quit the field, But stand in bold defiance. Descend, defend From all errors And earth&#39;s terrors Thy salvation Be our constant consolation."
  },
  "phrases": [
    {
      "label": "A",
      "bars": [
        1,
        2,
        3,
        4,
        5,
        6
      ],
      "strategy": "melody rises — breathes",
      "cycle": "stacked",
      "cycle_color": "accent",
      "lyrics": {
        "v1": "O Holy Spirit, enter in, And in our hearts Thy work be",
        "v2": "Give to Thy Word impressive pow&#39;r That in our hearts, from this good"
      }
    },
    {
      "label": "B",
      "bars": [
        7,
        8,
        9
      ],
      "strategy": "melody falls — breathes",
      "cycle": "stacked",
      "cycle_color": "accent",
      "lyrics": {
        "v1": "gin Thy Temple deign to make",
        "v2": "hour, As fire it may be glow"
      }
    },
    {
      "label": "C",
      "bars": [
        10,
        11,
        12
      ],
      "strategy": "melody rises — breathes",
      "cycle": "3rds CCW",
      "cycle_color": "leafred",
      "lyrics": {
        "v1": "us; Sun of the",
        "v2": "ing; That we con"
      }
    },
    {
      "label": "D",
      "bars": [
        13,
        14,
        15,
        16,
        17,
        18
      ],
      "strategy": "melody rises — breathes",
      "cycle": "4ths CCW",
      "cycle_color": "leafyellow",
      "lyrics": {
        "v1": "soul, Thou Light divine, Around and in us brightly shine, To joy and",
        "v2": "fess the Father, Son, And Thee, the Spirit, Three in One, Thy glory"
      }
    },
    {
      "label": "E",
      "bars": [
        19,
        20
      ],
      "strategy": "melody falls — breathes",
      "cycle": "stacked",
      "cycle_color": "accent",
      "lyrics": {
        "v1": "gladness wake us.",
        "v2": "ever showing."
      }
    },
    {
      "label": "F",
      "bars": [
        21,
        22,
        23,
        24,
        25
      ],
      "strategy": "melody falls — rests on a fermata",
      "cycle": "stacked",
      "cycle_color": "accent",
      "lyrics": {
        "v1": "That we to Thee Truly living, To Thee giving Prayer unceasing",
        "v2": "Stay Thou, guide now Our souls ever that they never May forsake Thee."
      }
    },
    {
      "label": "G",
      "bars": [
        26,
        27
      ],
      "strategy": "melody falls — breathes",
      "cycle": "stacked",
      "cycle_color": "accent",
      "lyrics": {
        "v1": "May in love be",
        "v2": "But by faith their"
      }
    },
    {
      "label": "H",
      "bars": [
        28,
        29
      ],
      "strategy": "melody falls — closes home",
      "cycle": "stacked",
      "cycle_color": "accent",
      "lyrics": {
        "v1": "still increasing.",
        "v2": "refuge make Thee."
      }
    }
  ],
  "assignments": [
    {
      "bar": 1,
      "rn": "I4",
      "mel": null,
      "lh_rom": "I6",
      "lh_qual": "",
      "lh_fig": "1332",
      "rh_rom": "V7i",
      "rh_qual": "",
      "rh_fig": "7332",
      "mood": "Warm",
      "source": "stacked_chords"
    },
    {
      "bar": 2,
      "rn": "I52",
      "mel": "B-4",
      "lh_rom": "I6",
      "lh_qual": "",
      "lh_fig": "1332",
      "rh_rom": "V7i",
      "rh_qual": "",
      "rh_fig": "7332",
      "mood": "Warm",
      "source": "stacked_chords"
    },
    {
      "bar": 3,
      "rn": "I4",
      "mel": "E-4",
      "lh_rom": "V",
      "lh_qual": "",
      "lh_fig": "533",
      "rh_rom": "I",
      "rh_qual": "",
      "rh_fig": "F33",
      "mood": "Lofting",
      "source": "jazz_progressions"
    },
    {
      "bar": 4,
      "rn": "V32",
      "mel": "C5",
      "lh_rom": "V",
      "lh_qual": "",
      "lh_fig": "533",
      "rh_rom": "I",
      "rh_qual": "",
      "rh_fig": "F33",
      "mood": "Resolving",
      "source": "jazz_progressions"
    },
    {
      "bar": 5,
      "rn": "I",
      "mel": null,
      "lh_rom": "I6",
      "lh_qual": "",
      "lh_fig": "1332",
      "rh_rom": "V7i",
      "rh_qual": "",
      "rh_fig": "7332",
      "mood": "Warm",
      "source": "stacked_chords"
    },
    {
      "bar": 6,
      "rn": "I74",
      "mel": "E-5",
      "lh_rom": "IVΔii",
      "lh_qual": "",
      "lh_fig": "1323",
      "rh_rom": "IΔiii",
      "rh_qual": "",
      "rh_fig": "7233",
      "mood": "Exploring",
      "source": "jazz_progressions"
    },
    {
      "bar": 7,
      "rn": "IV52",
      "mel": "B-4",
      "lh_rom": "IV",
      "lh_qual": "",
      "lh_fig": "433",
      "rh_rom": "Vii",
      "rh_qual": "",
      "rh_fig": "943",
      "mood": "Curling",
      "source": "stacked_chords"
    },
    {
      "bar": 8,
      "rn": "IV",
      "mel": "C5",
      "lh_rom": "I",
      "lh_qual": "",
      "lh_fig": "133",
      "rh_rom": "IV",
      "rh_qual": "",
      "rh_fig": "B33",
      "mood": "Landing",
      "source": "jazz_progressions"
    },
    {
      "bar": 9,
      "rn": "I52",
      "mel": "A-4",
      "lh_rom": "I6",
      "lh_qual": "",
      "lh_fig": "1332",
      "rh_rom": "V7i",
      "rh_qual": "",
      "rh_fig": "7332",
      "mood": "Warm",
      "source": "stacked_chords"
    },
    {
      "bar": 10,
      "rn": "I",
      "mel": "E-4",
      "lh_rom": "vi",
      "lh_qual": "",
      "lh_fig": "633",
      "rh_rom": "I",
      "rh_qual": "",
      "rh_fig": "F33",
      "mood": "Brooding",
      "source": "jazz_progressions"
    },
    {
      "bar": 11,
      "rn": "vi",
      "mel": null,
      "lh_rom": "V",
      "lh_qual": "",
      "lh_fig": "533",
      "rh_rom": "vi",
      "rh_qual": "",
      "rh_fig": "D33",
      "mood": "Pivoting",
      "source": "jazz_progressions"
    },
    {
      "bar": 12,
      "rn": "V6",
      "mel": "B-4",
      "lh_rom": "V",
      "lh_qual": "",
      "lh_fig": "533",
      "rh_rom": "I",
      "rh_qual": "",
      "rh_fig": "F33",
      "mood": "Resolving",
      "source": "jazz_progressions"
    },
    {
      "bar": 13,
      "rn": "I43",
      "mel": "E-4",
      "lh_rom": "V",
      "lh_qual": "",
      "lh_fig": "533",
      "rh_rom": "I",
      "rh_qual": "",
      "rh_fig": "F33",
      "mood": "Lofting",
      "source": "jazz_progressions"
    },
    {
      "bar": 14,
      "rn": "V52",
      "mel": "C5",
      "lh_rom": "V7ii",
      "lh_qual": "",
      "lh_fig": "2323",
      "rh_rom": "ii7iii",
      "rh_qual": "",
      "rh_fig": "8233",
      "mood": "Stepping",
      "source": "jazz_progressions"
    },
    {
      "bar": 15,
      "rn": "ii7",
      "mel": null,
      "lh_rom": "ii",
      "lh_qual": "",
      "lh_fig": "233",
      "rh_rom": "IV",
      "rh_qual": "",
      "rh_fig": "B33",
      "mood": "Gladdening",
      "source": "jazz_progressions"
    },
    {
      "bar": 16,
      "rn": "IV52",
      "mel": "E-5",
      "lh_rom": "IV6",
      "lh_qual": "",
      "lh_fig": "4332",
      "rh_rom": "IΔi",
      "rh_qual": "",
      "rh_fig": "A332",
      "mood": "Lifted",
      "source": "stacked_chords"
    },
    {
      "bar": 17,
      "rn": "IV32",
      "mel": "B-4",
      "lh_rom": "IV",
      "lh_qual": "",
      "lh_fig": "433",
      "rh_rom": "Vii",
      "rh_qual": "",
      "rh_fig": "943",
      "mood": "Curling",
      "source": "stacked_chords"
    },
    {
      "bar": 18,
      "rn": "IV6",
      "mel": "C5",
      "lh_rom": "I",
      "lh_qual": "",
      "lh_fig": "133",
      "rh_rom": "IV",
      "rh_qual": "",
      "rh_fig": "B33",
      "mood": "Landing",
      "source": "jazz_progressions"
    },
    {
      "bar": 19,
      "rn": "I7",
      "mel": "A-4",
      "lh_rom": "I6",
      "lh_qual": "",
      "lh_fig": "1332",
      "rh_rom": "V7i",
      "rh_qual": "",
      "rh_fig": "7332",
      "mood": "Warm",
      "source": "stacked_chords"
    },
    {
      "bar": 20,
      "rn": "I",
      "mel": "E-4",
      "lh_rom": "I",
      "lh_qual": "",
      "lh_fig": "133",
      "rh_rom": "IV",
      "rh_qual": "",
      "rh_fig": "B33",
      "mood": "Exploring",
      "source": "jazz_progressions"
    },
    {
      "bar": 21,
      "rn": "I64",
      "mel": "B-4",
      "lh_rom": "I6",
      "lh_qual": "",
      "lh_fig": "1332",
      "rh_rom": "V7i",
      "rh_qual": "",
      "rh_fig": "7332",
      "mood": "Warm",
      "source": "stacked_chords"
    },
    {
      "bar": 23,
      "rn": "I",
      "mel": "G4",
      "lh_rom": "vi",
      "lh_qual": "",
      "lh_fig": "633",
      "rh_rom": "I",
      "rh_qual": "",
      "rh_fig": "F33",
      "mood": "Brooding",
      "source": "jazz_progressions"
    },
    {
      "bar": 24,
      "rn": "vi",
      "mel": "G4",
      "lh_rom": "IV",
      "lh_qual": "",
      "lh_fig": "433",
      "rh_rom": "vi",
      "rh_qual": "",
      "rh_fig": "D33",
      "mood": "Consoling",
      "source": "jazz_progressions"
    },
    {
      "bar": 25,
      "rn": "IV7",
      "mel": "G4",
      "lh_rom": "IV",
      "lh_qual": "",
      "lh_fig": "433",
      "rh_rom": "vi",
      "rh_qual": "",
      "rh_fig": "D33",
      "mood": "Grieving",
      "source": "jazz_progressions"
    },
    {
      "bar": 26,
      "rn": "IV",
      "mel": "E-5",
      "lh_rom": "IV6",
      "lh_qual": "",
      "lh_fig": "4332",
      "rh_rom": "IΔi",
      "rh_qual": "",
      "rh_fig": "A332",
      "mood": "Lifted",
      "source": "stacked_chords"
    },
    {
      "bar": 27,
      "rn": "IV43",
      "mel": "C5",
      "lh_rom": "I",
      "lh_qual": "",
      "lh_fig": "133",
      "rh_rom": "IV",
      "rh_qual": "",
      "rh_fig": "B33",
      "mood": "Landing",
      "source": "jazz_progressions"
    },
    {
      "bar": 28,
      "rn": "I",
      "mel": "A-4",
      "lh_rom": "I6",
      "lh_qual": "",
      "lh_fig": "1332",
      "rh_rom": "V7i",
      "rh_qual": "",
      "rh_fig": "7332",
      "mood": "Warm",
      "source": "stacked_chords"
    }
  ],
  "total_bars": 29
}